hi_chem/__init__.py
hi_chem/__version__.py
hi_chem/app.py
hi_chem/conformer.py
hi_chem/dimensionality_reduction.py
hi_chem/featurize.py
hi_chem/translate.py
hi_chem/view.py
hi_chem-0.1.6.dist-info/LICENSE
hi_chem-0.1.6.dist-info/METADATA
hi_chem-0.1.6.dist-info/WHEEL
hi_chem-0.1.6.dist-info/entry_points.txt
hi_chem-0.1.6.dist-info/top_level.txt
hi_chem-0.1.6.dist-info/RECORD
