Metadata-Version: 2.2
Name: hi-chem
Version: 0.1.6
Summary: hi-chem - A template Python package for Harms Informatics
Home-page: https://github.com/HarmsInformatics/hi-chem
Author: Nate Harms
Author-email: harmsinformatics@gmail.com
License: MIT
Keywords: package development template
Classifier: Development Status :: 4 - Beta
Classifier: Intended Audience :: Developers
Classifier: Programming Language :: Python :: 3.11
Requires-Python: >=3.11
License-File: LICENSE
Requires-Dist: numpy
Requires-Dist: requests
Requires-Dist: pandas
Requires-Dist: seaborn
Requires-Dist: matplotlib
Requires-Dist: typer
Requires-Dist: rdkit
Requires-Dist: py3dmol
Requires-Dist: jupyter
Requires-Dist: ipython
Requires-Dist: scikit-learn
Requires-Dist: umap-learn
Dynamic: author
Dynamic: author-email
Dynamic: classifier
Dynamic: description
Dynamic: description-content-type
Dynamic: home-page
Dynamic: keywords
Dynamic: license
Dynamic: requires-dist
Dynamic: requires-python
Dynamic: summary
